molad/__init__.py
molad/helper.py
molad-0.0.12.dist-info/METADATA
molad-0.0.12.dist-info/WHEEL
molad-0.0.12.dist-info/licenses/LICENSE
molad-0.0.12.dist-info/RECORD
