Metadata-Version: 2.4
Name: molad
Version: 0.0.12
Summary: Molad for Python
Project-URL: Homepage, https://github.com/chaimchaikin/molad
Project-URL: Bug Tracker, https://github.com/chaimchaikin/molad/issues
Author-email: Chaim Chaikin <molad@chaimchaikin.com>
License-File: LICENSE
Classifier: License :: OSI Approved :: MIT License
Classifier: Operating System :: OS Independent
Classifier: Programming Language :: Python :: 3
Requires-Python: >=3.7
Requires-Dist: hdate>=1.1.2
